BluePIL/__init__.py
bluepil-0.1.5.dist-info/licenses/LICENCE
bluepil-0.1.5.dist-info/METADATA
bluepil-0.1.5.dist-info/WHEEL
bluepil-0.1.5.dist-info/top_level.txt
bluepil-0.1.5.dist-info/RECORD
