Metadata-Version: 2.4
Name: BluePIL
Version: 0.1.5
Summary: Automatic memory management for Pillow - take the blue pill
Author-email: wanmanewan <noreply.ewanm@gmail.com>
License: MIT
Project-URL: Homepage, https://github.com/ewan-m/bluepil
Project-URL: Issues, https://github.com/ewan-m/bluepil/issues
Project-URL: Repository, https://github.com/ewan-m/bluepil
Keywords: pillow,PIL,image,memory,cleanup
Classifier: Development Status :: 4 - Beta
Classifier: Intended Audience :: Developers
Classifier: License :: OSI Approved :: MIT License
Classifier: Programming Language :: Python :: 3
Classifier: Programming Language :: Python :: 3.8
Classifier: Programming Language :: Python :: 3.9
Classifier: Programming Language :: Python :: 3.10
Classifier: Programming Language :: Python :: 3.11
Classifier: Programming Language :: Python :: 3.12
Classifier: Topic :: Multimedia :: Graphics
Requires-Python: >=3.8
License-File: LICENCE
Requires-Dist: Pillow>=8.0.0
Dynamic: license-file
